LICENSE
MANIFEST.in
README.md
requirements.txt
setup.py
wagtail_materializecss/__init__.py
wagtail_materializecss/blocks.py
wagtail_materializecss/colors.py
wagtail_materializecss/components.py
wagtail_materializecss/grid.py
wagtail_materializecss/javascript.py
wagtail_materializecss/models.py
wagtail_materializecss.egg-info/PKG-INFO
wagtail_materializecss.egg-info/SOURCES.txt
wagtail_materializecss.egg-info/dependency_links.txt
wagtail_materializecss.egg-info/requires.txt
wagtail_materializecss.egg-info/top_level.txt
wagtail_materializecss/static/materialize/LICENSE
wagtail_materializecss/static/materialize/README.md
wagtail_materializecss/static/materialize/css/materialize.css
wagtail_materializecss/static/materialize/css/materialize.min.css
wagtail_materializecss/static/materialize/fonts/roboto/Roboto-Bold.woff
wagtail_materializecss/static/materialize/fonts/roboto/Roboto-Bold.woff2
wagtail_materializecss/static/materialize/fonts/roboto/Roboto-Light.woff
wagtail_materializecss/static/materialize/fonts/roboto/Roboto-Light.woff2
wagtail_materializecss/static/materialize/fonts/roboto/Roboto-Medium.woff
wagtail_materializecss/static/materialize/fonts/roboto/Roboto-Medium.woff2
wagtail_materializecss/static/materialize/fonts/roboto/Roboto-Regular.woff
wagtail_materializecss/static/materialize/fonts/roboto/Roboto-Regular.woff2
wagtail_materializecss/static/materialize/fonts/roboto/Roboto-Thin.woff
wagtail_materializecss/static/materialize/fonts/roboto/Roboto-Thin.woff2
wagtail_materializecss/static/materialize/js/materialize.js
wagtail_materializecss/static/materialize/js/materialize.min.js
wagtail_materializecss/static/wagtail_materializecss/css/custom.css
wagtail_materializecss/static/wagtail_materializecss/js/custom.js
wagtail_materializecss/templates/wagtail_materializecss/base.html
wagtail_materializecss/templates/wagtail_materializecss/base_with_user.html
wagtail_materializecss/templates/wagtail_materializecss/dynamic_css.html
wagtail_materializecss/templates/wagtail_materializecss/components/badge.html
wagtail_materializecss/templates/wagtail_materializecss/components/breadcrumb.html
wagtail_materializecss/templates/wagtail_materializecss/components/button.html
