Metadata-Version: 1.1
Name: wagtail-materializecss
Version: 0.0.5
Summary: Wagtail CMS materialize css components and javascript items as blocks.
Home-page: https://github.com/justengel-django/wagtail_materializecss
Author: Justin Engel
Author-email: jtengel08@gmail.com
License: MIT License
Download-URL: https://github.com/justengel-django/wagtail_materializecss/archive/v0.0.5.tar.gz
Platform: any
Classifier: Environment :: Web Environment
Classifier: Framework :: Wagtail
Classifier: Framework :: Wagtail :: 2
Classifier: Framework :: Django
Classifier: Framework :: Django :: 2.0
Classifier: Intended Audience :: Developers
Classifier: License :: OSI Approved :: MIT License
Classifier: Operating System :: OS Independent
Classifier: Programming Language :: Python
Classifier: Programming Language :: Python :: 3
Classifier: Programming Language :: Python :: 3.5
Classifier: Programming Language :: Python :: 3.6
Classifier: Topic :: Internet :: WWW/HTTP
Classifier: Topic :: Internet :: WWW/HTTP :: Dynamic Content
